json_validator/__init__.py
json_validator/extractor.py
json_validator/validator.py
json_validator-1.0.dist-info/DESCRIPTION.rst
json_validator-1.0.dist-info/METADATA
json_validator-1.0.dist-info/RECORD
json_validator-1.0.dist-info/WHEEL
json_validator-1.0.dist-info/metadata.json
json_validator-1.0.dist-info/top_level.txt
