Metadata-Version: 2.0
Name: json-validator
Version: 1.0
Summary: Provide decorator for validating json parameters passed to function. Can be used for validation of json parameters sent to Flask.
Home-page: https://github.com/sliwinski-milosz/json_validator
Author: Milosz Sliwinski
Author-email: sliwinski.milosz@gmail.com
License: The MIT License (MIT)
Requires-Dist: jsonschema (==2.5.1)
